{
  "id": "increase_content_target_intensity_v1",
  "type": "actionTypes",
  "attributes": {
    "params": [
      {
        "key": "step",
        "type": "float",
        "default": "5.00",
        "gteq": 0.0,
        "lteq": 100.0,
        "optional": true
      },
      {
        "key": "fadeMilliSecs",
        "type": "integer",
        "default": "2000",
        "gteq": 0,
        "lteq": 1800000000,
        "optional": true
      },
      {
        "key": "delayMilliSecs",
        "type": "integer",
        "default": "0",
        "gteq": 0,
        "lteq": 1800000000,
        "optional": true
      }
    ]
  }
}